{"inkVersion":20,"root":[["ev",{"VAR?":"given_costume"},"/ev",[{"->":".^.b","c":true},{"b":["^ ",{"->":"subsequent"},{"->":"0.4"},null]}],"nop","\n",{"#":"char ken_spirit"},"^Oh, hello again.","\n","^Find any good costumes?","\n",{"#":"char cleo"},"^Yeah, actually.","\n","^Well, maybe.","\n","^Here.","\n",{"#":"char ken_spirit"},"^...A suit?","\n",{"#":"char cleo"},"^Yeah, it was the best I could find. It's not great.","\n",{"#":"char ken_spirit"},"^Eh... I actually like it.","\n","^Makes me feel all businessy and... professional daddy-like.","\n","^I think my son will like it.","\n",{"#":"char cleo"},"^Oh, you have a son?","\n",{"#":"char ken_spirit"},"^Yeah. I dress up with him every year.","\n","^It's one of our favorite things to do together.","\n",{"#":"char cleo"},"^Aw... that's really sweet.","\n","^Reminds me of someone else, actually.","\n",{"#":"char ken_spirit"},"^Hm?","\n",{"#":"char cleo"},"^Oh, nothing.","\n","^Glad you like the costume!","\n",{"#":"char ken_spirit"},"^Thanks for the help!","\n","end",["done",{"#f":5,"#n":"g-0"}],null],"done",{"subsequent":[{"#":"char ken_spirit"},"^Maybe this suit will make me sneeze less somehow...","\n","end",{"#f":1}],"global decl":["ev",false,{"VAR=":"given_costume"},"/ev","end",null],"#f":1}],"listDefs":{}}