{"inkVersion":20,"root":[["ev",{"VAR?":"given_costume"},"/ev",[{"->":".^.b","c":true},{"b":["^ ",{"->":"subsequent"},{"->":"0.4"},null]}],"nop","\n",{"#":"char chrysantha"},"^Oh, h-hi!","\n",{"#":"char cleo"},"^Uh... have you found those lights you were looking for?","\n",{"#":"char chrysantha"},"^Um... not really. I kinda got sidetracked looking at other decorations...","\n","^Y'know... just trying to make my dorm look nice for the season...","\n","^Ha ha...","\n",{"#":"char cleo"},"^Uh... you don't seem okay.","\n",{"#":"char chrysantha"},"^Okay yeah I'm not okay at all I'm very stressed out I have homework to do I have midterms coming up I have to get a job sometime I have to get decorations for my dorm oh my god there's so much I have to do AAAAAAAAAAAAAAAAAHHHHHH","\n",{"#":"char cleo"},"^Whoa, whoa! Calm down!","\n","^Look, I, uh...","\n","^I've been there a few years ago. All that stuff sucks, but you'll get through it.","\n",{"#":"char chrysantha"},"^Okay...","\n",{"#":"char cleo"},"^Hey, in the meantime, I found something you might like.","\n",{"#":"char chrysantha"},"^O-oh... is that a vampire costume?","\n","^Heh... I like it.","\n","^I don't usually dress up, but... maybe I should try it this year. Might help get my mind off things.","\n",{"#":"char cleo"},"^Yeah, definitely!","\n","^Good luck with everything.","\n",{"#":"char chrysantha"},"^Oh, thanks!","\n","end",["done",{"#f":5,"#n":"g-0"}],null],"done",{"subsequent":[{"#":"char chrysantha"},"^Hey, thanks again for the encouragement.","\n","^...And the costume. It's pretty cool.","\n","end",{"#f":1}],"global decl":["ev",false,{"VAR=":"given_costume"},"/ev","end",null],"#f":1}],"listDefs":{}}