{"inkVersion":20,"root":[[{"#":"char ken"},{"#":"music HumanKen"},"^Mmmmgh...","\n",{"#":"char cleo"},"^Uh... everything good over here?","\n",{"#":"char ken"},"^Just trying to find a costume for my son.","\n",{"#":"char cleo"},"^Oh. There are more kids' costumes over there if you want to look.","\n",{"#":"char ken"},"^I know. I shop here every year. I'm good.","\n",{"#":"char cleo"},{"#":"emotion tired"},"^Okay, then...","\n","end",["done",{"#f":5,"#n":"g-0"}],null],"done",{"#f":1}],"listDefs":{}}